pbbt/__init__.py
pbbt/check.py
pbbt/core.py
pbbt/ctl.py
pbbt/load.py
pbbt/run.py
pbbt/setup.py
pbbt/std.py
pbbt/ui.py
pbbt-0.2.0.dist-info/LICENSE
pbbt-0.2.0.dist-info/METADATA
pbbt-0.2.0.dist-info/WHEEL
pbbt-0.2.0.dist-info/entry_points.txt
pbbt-0.2.0.dist-info/top_level.txt
pbbt-0.2.0.dist-info/RECORD
