Metadata-Version: 2.1
Name: pbbt
Version: 0.2.0
Summary: Pluggable Black-Box Testing toolkit
Home-page: https://github.com/prometheusresearch/pbbt
Download-URL: http://pypi.python.org/pypi/pbbt
Author: Kirill Simonov (Prometheus Research, LLC)
Author-email: xi@resolvent.net
License: MIT
Classifier: Development Status :: 2 - Pre-Alpha
Classifier: Environment :: Console
Classifier: Intended Audience :: Developers
Classifier: License :: OSI Approved :: MIT License
Classifier: Operating System :: POSIX :: Linux
Classifier: Programming Language :: Python
Classifier: Programming Language :: Python :: 3
Classifier: Topic :: Utilities
License-File: LICENSE
Requires-Dist: PyYAML
